dotty_dictionary/__init__.py
dotty_dictionary/_dotty.py
dotty_dictionary/_dotty_dictionary.py
dotty_dictionary-1.2.0.dist-info/AUTHORS.md
dotty_dictionary-1.2.0.dist-info/LICENSE
dotty_dictionary-1.2.0.dist-info/METADATA
dotty_dictionary-1.2.0.dist-info/WHEEL
dotty_dictionary-1.2.0.dist-info/RECORD
